toga_flask/__init__.py
toga_flask/app.py
toga_flask-0.3.0.dev38.dist-info/LICENSE
toga_flask-0.3.0.dev38.dist-info/METADATA
toga_flask-0.3.0.dev38.dist-info/WHEEL
toga_flask-0.3.0.dev38.dist-info/top_level.txt
toga_flask-0.3.0.dev38.dist-info/RECORD
